altspell_plugins/__init__.py
altspell_plugins-0.2.2.dist-info/WHEEL
altspell_plugins-0.2.2.dist-info/METADATA
altspell_plugins-0.2.2.dist-info/RECORD
